shipyard_googlecloud/__init__.py
shipyard_googlecloud/cli/__init__.py
shipyard_googlecloud/cli/authtest.py
shipyard_googlecloud/cli/download.py
shipyard_googlecloud/cli/move.py
shipyard_googlecloud/cli/remove.py
shipyard_googlecloud/cli/upload.py
shipyard_googlecloud/googlecloud.py
shipyard_googlecloud/utils.py
shipyard_googlecloud-0.2.0.dist-info/METADATA
shipyard_googlecloud-0.2.0.dist-info/WHEEL
shipyard_googlecloud-0.2.0.dist-info/RECORD
