Metadata-Version: 2.1
Name: shipyard-googlecloud
Version: 0.2.0
Summary: A local client for connecting and working with Google Cloud Service
License: Apache 2.0
Author: wrp801
Author-email: wespoulsen@gmail.com
Requires-Python: >=3.9,<3.10
Classifier: License :: Other/Proprietary License
Classifier: Programming Language :: Python :: 3
Classifier: Programming Language :: Python :: 3.9
Requires-Dist: google-cloud-storage (>=2.15.0,<3.0.0)
Requires-Dist: httplib2 (==0.15.0)
Requires-Dist: shipyard-bp-utils (>=1.2.1,<2.0.0)
